apolloMusicRipper/config.py
apolloMusicRipper/run.py
apolloRipper/__init__.py
apolloRipper/config.py
apolloRipper/run.py
apolloRipper-0.3.dist-info/DESCRIPTION.rst
apolloRipper-0.3.dist-info/METADATA
apolloRipper-0.3.dist-info/RECORD
apolloRipper-0.3.dist-info/WHEEL
apolloRipper-0.3.dist-info/metadata.json
apolloRipper-0.3.dist-info/top_level.txt
