Metadata-Version: 2.0
Name: apolloRipper
Version: 0.3
Summary: The ripper and tagger for Apollo
Home-page: https://github.com/ebber/apolloRipper
Author: Erik Beitel
Author-email: erik.beitel@gmail.com
License: UNKNOWN
Download-URL: https://github.com/ebber/apolloRipper/archive/0.3.tar.gz
Keywords: audio,youtube ripper
Platform: UNKNOWN
Requires-Dist: ffprobe
Requires-Dist: logging
Requires-Dist: spotipy
Requires-Dist: youtube-dl
